<?xml version="1.0" encoding="utf-8"?><ArrayOfOrders xmlns:xsi="http://www.w3.org/2001/XMLSchema-instance" xmlns:xsd="http://www.w3.org/2001/XMLSchema"><Orders><_orderId>1</_orderId><_customerName>Esther Bat Zion Levinson</_customerName><_email>ebzlevinson@gmail.com</_email><_address>Haroe 20/2</_address><_orderDate>2022-06-16T14:39:06.9091336+03:00</_orderDate><_shippingDate>2022-06-17T14:39:06.9091336+03:00</_shippingDate><_deliveryDate>2022-06-18T14:39:06.9091336+03:00</_deliveryDate></Orders><Orders><_orderId>2</_orderId><_customerName>Tamar Smietanski</_customerName><_email>tamarsmiet@gmail.com</_email><_address>Haroe 20/2</_address><_orderDate>2022-08-31T14:39:07.0753387+03:00</_orderDate><_shippingDate>2022-08-31T14:39:07.0753387+03:00</_shippingDate><_deliveryDate>2022-08-31T14:39:07.0753387+03:00</_deliveryDate></Orders><Orders><_orderId>3</_orderId><_customerName>Israel Israeli</_customerName><_email>israel@gmail.com</_email><_address>buksboim 12</_address><_orderDate>2021-08-14T14:39:07.1358197+03:00</_orderDate><_shippingDate>2021-08-22T14:39:07.1358197+03:00</_shippingDate><_deliveryDate>2021-08-26T14:39:07.1358197+03:00</_deliveryDate></Orders><Orders><_orderId>4</_orderId><_customerName>Avraham Cohen</_customerName><_email>avic@gmail.com</_email><_address>tlalim 21</_address><_orderDate>2022-08-25T14:39:07.1610668+03:00</_orderDate><_shippingDate>2022-09-01T14:39:07.1610668+03:00</_shippingDate><_deliveryDate>2022-09-02T14:39:07.1610668+03:00</_deliveryDate></Orders><Orders><_orderId>5</_orderId><_customerName>Itschak</_customerName><_email>I@gmail.com</_email><_address>my address</_address><_orderDate>0001-01-01T00:00:00</_orderDate><_shippingDate>0001-01-01T00:00:00</_shippingDate><_deliveryDate>0001-01-01T00:00:00</_deliveryDate></Orders><Orders><_orderId>6</_orderId><_customerName>Alice</_customerName><_email>alice@gmail.com</_email><_address>jerusalem</_address><_orderDate>2023-01-25T15:00:46.5916892+02:00</_orderDate><_shippingDate>0001-01-01T00:00:00</_shippingDate><_deliveryDate>0001-01-01T00:00:00</_deliveryDate></Orders><Orders><_orderId>7</_orderId><_customerName>Bob</_customerName><_email>bob@gmail.com</_email><_address>talpiot</_address><_orderDate>2023-01-25T15:04:30.2793864+02:00</_orderDate><_shippingDate>0001-01-01T00:00:00</_shippingDate><_deliveryDate>0001-01-01T00:00:00</_deliveryDate></Orders></ArrayOfOrders>