<?xml version="1.0" encoding="utf-8"?>
<ArrayOfOrders xmlns:xsi="http://www.w3.org/2001/XMLSchema-instance" xmlns:xsd="http://www.w3.org/2001/XMLSchema">
  <Orders>
    <_orderId>2</_orderId>
    <_customerName>Tamar Smietanski</_customerName>
    <_email>tamarsmiet@gmail.com</_email>
    <_address>Haroe 20/2</_address>
    <_orderDate>2022-08-31T14:39:07.0753387+03:00</_orderDate>
    <_shippingDate>2022-08-31T14:39:07.0753387+03:00</_shippingDate>
    <_deliveryDate>2022-08-31T14:39:07.0753387+03:00</_deliveryDate>
  </Orders>
  <Orders>
    <_orderId>3</_orderId>
    <_customerName>Israel Israeli</_customerName>
    <_email>israel@gmail.com</_email>
    <_address>buksboim 12</_address>
    <_orderDate>2021-08-14T14:39:07.1358197+03:00</_orderDate>
    <_shippingDate>2021-08-22T14:39:07.1358197+03:00</_shippingDate>
    <_deliveryDate>2021-08-26T14:39:07.1358197+03:00</_deliveryDate>
  </Orders>
  <Orders>
    <_orderId>1</_orderId>
    <_customerName>Esther Bat Zion Levinson</_customerName>
    <_email>ebzlevinson@gmail.com</_email>
    <_address>Haroe 20/2</_address>
    <_orderDate>2022-06-16T14:39:06.9091336+03:00</_orderDate>
    <_shippingDate>2023-02-25T21:21:57.292783+02:00</_shippingDate>
    <_deliveryDate>2023-02-25T21:41:19.2389477+02:00</_deliveryDate>
  </Orders>
  <Orders>
    <_orderId>12</_orderId>
    <_customerName>smit</_customerName>
    <_email>hsmiet@gmail.com</_email>
    <_address>shechter 4</_address>
    <_orderDate>2023-02-25T22:40:01.5824764+02:00</_orderDate>
    <_shippingDate>2023-02-25T22:42:05.6497913+02:00</_shippingDate>
    <_deliveryDate>2023-02-25T22:45:09.2442942+02:00</_deliveryDate>
  </Orders>
  <Orders>
    <_orderId>9</_orderId>
    <_customerName>viki</_customerName>
    <_email>viki@gmail.com</_email>
    <_address>yaakov elazar 17</_address>
    <_orderDate>2023-02-25T22:17:22.2531699+02:00</_orderDate>
    <_shippingDate>2023-02-25T22:43:33.3249267+02:00</_shippingDate>
    <_deliveryDate>2023-02-25T22:45:14.2684985+02:00</_deliveryDate>
  </Orders>
  <Orders>
    <_orderId>10</_orderId>
    <_customerName>Sarah</_customerName>
    <_email>sarah@gmail.com</_email>
    <_address>revivim 15</_address>
    <_orderDate>2023-02-25T22:18:39.2151695+02:00</_orderDate>
    <_shippingDate>2023-02-25T22:45:03.1636254+02:00</_shippingDate>
    <_deliveryDate>2023-02-25T22:45:21.2928989+02:00</_deliveryDate>
  </Orders>
  <Orders>
    <_orderId>11</_orderId>
    <_customerName>yossef</_customerName>
    <_email>coco@gmail.com</_email>
    <_address>hadolev 7</_address>
    <_orderDate>2023-02-25T22:19:46.0852752+02:00</_orderDate>
    <_shippingDate>2023-02-25T22:45:06.2246362+02:00</_shippingDate>
    <_deliveryDate>2023-02-25T22:45:26.3195389+02:00</_deliveryDate>
  </Orders>
  <Orders>
    <_orderId>13</_orderId>
    <_customerName>waffel Bar</_customerName>
    <_email>waffelbae@gmail.com</_email>
    <_address>queniyon ramot</_address>
    <_orderDate>2023-02-26T13:16:43.6651394+02:00</_orderDate>
    <_shippingDate>2023-02-26T13:16:47.4535852+02:00</_shippingDate>
    <_deliveryDate>2023-02-26T13:16:51.4876301+02:00</_deliveryDate>
  </Orders>
  <Orders>
    <_orderId>14</_orderId>
    <_customerName>dgrf d</_customerName>
    <_email>fcyvg@g.com</_email>
    <_address>vg</_address>
    <_orderDate>2023-02-26T13:17:43.8058491+02:00</_orderDate>
    <_shippingDate>2023-02-26T13:17:47.1642044+02:00</_shippingDate>
    <_deliveryDate>2023-02-26T13:19:08.7344206+02:00</_deliveryDate>
  </Orders>
  <Orders>
    <_orderId>15</_orderId>
    <_customerName>rftgy</_customerName>
    <_email>rctt@g.vom</_email>
    <_address>gv</_address>
    <_orderDate>2023-02-26T13:18:41.4887959+02:00</_orderDate>
    <_shippingDate>2023-02-26T13:19:14.7660424+02:00</_shippingDate>
    <_deliveryDate>2023-02-26T13:19:23.7872749+02:00</_deliveryDate>
  </Orders>
  <Orders>
    <_orderId>16</_orderId>
    <_customerName>rrrr</_customerName>
    <_email>r@g.com</_email>
    <_address>rrrrrrrrr</_address>
    <_orderDate>2023-02-26T13:23:12.9573114+02:00</_orderDate>
    <_shippingDate>2023-02-26T13:23:23.9667618+02:00</_shippingDate>
    <_deliveryDate>2023-02-26T13:24:22.7968644+02:00</_deliveryDate>
  </Orders>
  <Orders>
    <_orderId>17</_orderId>
    <_customerName>itsMe</_customerName>
    <_email>me@g.com</_email>
    <_address>myaddress</_address>
    <_orderDate>2023-02-26T13:40:52.6206191+02:00</_orderDate>
    <_shippingDate>2023-02-26T17:14:08.9192496+02:00</_shippingDate>
    <_deliveryDate>2023-02-26T17:14:56.9167192+02:00</_deliveryDate>
  </Orders>
  <Orders>
    <_orderId>21</_orderId>
    <_customerName>aaa</_customerName>
    <_email>e@gmail.com</_email>
    <_address>aaa</_address>
    <_orderDate>2023-02-26T19:06:12.6550443+02:00</_orderDate>
    <_shippingDate>2023-02-26T19:06:44.9726535+02:00</_shippingDate>
    <_deliveryDate>0001-01-01T00:00:00</_deliveryDate>
  </Orders>
  <Orders>
    <_orderId>19</_orderId>
    <_customerName>tt</_customerName>
    <_email>t@g.com</_email>
    <_address>tttt</_address>
    <_orderDate>2023-02-26T18:26:07.0046116+02:00</_orderDate>
    <_shippingDate>2023-02-26T19:07:20.7768317+02:00</_shippingDate>
    <_deliveryDate>0001-01-01T00:00:00</_deliveryDate>
  </Orders>
  <Orders>
    <_orderId>18</_orderId>
    <_customerName>shoulamit</_customerName>
    <_email>shoula@g.com</_email>
    <_address>bne brak</_address>
    <_orderDate>2023-02-26T18:15:08.8329944+02:00</_orderDate>
    <_shippingDate>2023-02-26T18:26:42.1835006+02:00</_shippingDate>
    <_deliveryDate>2023-02-26T19:07:25.8314049+02:00</_deliveryDate>
  </Orders>
  <Orders>
    <_orderId>20</_orderId>
    <_customerName>Sarah Miryam</_customerName>
    <_email>saram@gmail.com</_email>
    <_address>Africa</_address>
    <_orderDate>2023-02-26T18:30:44.6504021+02:00</_orderDate>
    <_shippingDate>2023-02-26T19:07:33.8644273+02:00</_shippingDate>
    <_deliveryDate>0001-01-01T00:00:00</_deliveryDate>
  </Orders>
</ArrayOfOrders>